segtools/__init__.py
segtools/aggregation.py
segtools/bed.py
segtools/common.py
segtools/compare.py
segtools/feature_distance.py
segtools/flatten.py
segtools/gff.py
segtools/gmtk_parameters.py
segtools/html.py
segtools/length_distribution.py
segtools/mnemonics.py
segtools/nucleotide_frequency.py
segtools/overlap.py
segtools/preprocess.py
segtools/relabel.py
segtools/signal_distribution.py
segtools/transition.py
segtools/version.py
segtools/R/__init__.py
segtools/R/aggregation.R
segtools/R/common.R
segtools/R/dinucleotide.R
segtools/R/distance.R
segtools/R/length.R
segtools/R/overlap.R
segtools/R/signal.R
segtools/R/track_statistics.R
segtools/R/transition.R
segtools/resources/__init__.py
segtools/resources/aggregation_div.tmpl
segtools/resources/aggregation_gene_div.tmpl
segtools/resources/distance_div.tmpl
segtools/resources/gmtk_div.tmpl
segtools/resources/html_footer.tmpl
segtools/resources/html_header.tmpl
segtools/resources/length_div.tmpl
segtools/resources/mnemonic_div.tmpl
segtools/resources/nucleotide_div.tmpl
segtools/resources/overlap_div.tmpl
segtools/resources/signal_div.tmpl
segtools/resources/transition_div.tmpl
segtools-1.3.0.dist-info/COPYING
segtools-1.3.0.dist-info/LICENSE
segtools-1.3.0.dist-info/METADATA
segtools-1.3.0.dist-info/WHEEL
segtools-1.3.0.dist-info/entry_points.txt
segtools-1.3.0.dist-info/top_level.txt
segtools-1.3.0.dist-info/RECORD
